commands/__init__.py
commands/one_api_eval_file.py
commands/one_api_eval_one.py
eval/__init__.py
eval/one_ai_eval.py
prompt_template/__init__.py
prompt_template/eval_prompt_template.json
prompt_template/prompter.py
utils/__init__.py
utils/data_utils.py
one_eval-0.1.2.dist-info/LICENSE
one_eval-0.1.2.dist-info/METADATA
one_eval-0.1.2.dist-info/WHEEL
one_eval-0.1.2.dist-info/entry_points.txt
one_eval-0.1.2.dist-info/top_level.txt
one_eval-0.1.2.dist-info/RECORD
